LICENSE
MANIFEST.in
README.md
setup.py
mach9/__init__.py
mach9/app.py
mach9/blueprints.py
mach9/config.py
mach9/exceptions.py
mach9/handlers.py
mach9/http.py
mach9/log.py
mach9/request.py
mach9/response.py
mach9/router.py
mach9/server.py
mach9/signal.py
mach9/static.py
mach9/testing.py
mach9/timer.py
mach9/views.py
mach9/websocket.py
mach9.egg-info/PKG-INFO
mach9.egg-info/SOURCES.txt
mach9.egg-info/dependency_links.txt
mach9.egg-info/requires.txt
mach9.egg-info/top_level.txt