Metadata-Version: 1.1
Name: mach9
Version: 0.0.4
Summary: a web application framework based ASGI and async/await.
Home-page: https://github.com/silver-castle/mach9
Author: 38elements
Author-email: UNKNOWN
License: MIT License
Platform: UNKNOWN
Classifier: Development Status :: 2 - Pre-Alpha
Classifier: Environment :: Web Environment
Classifier: License :: OSI Approved :: MIT License
Classifier: Programming Language :: Python :: 3.6
